greendeck_helloworld/__init__.py
greendeck_helloworld/src/elasticsearch/__init__.py
greendeck_helloworld/src/elasticsearch/elasticsearch.py
greendeck_helloworld/src/mongodb/__init__.py
greendeck_helloworld/src/mongodb/mongodb.py
greendeck_helloworld-0.0.2.dist-info/LICENSE
greendeck_helloworld-0.0.2.dist-info/METADATA
greendeck_helloworld-0.0.2.dist-info/WHEEL
greendeck_helloworld-0.0.2.dist-info/top_level.txt
greendeck_helloworld-0.0.2.dist-info/RECORD
